LICENSE
README.md
setup.py
src/dbgpu/__init__.py
src/dbgpu/__main__.py
src/dbgpu/constants.py
src/dbgpu/data.pkl
src/dbgpu/db.py
src/dbgpu/gpu.py
src/dbgpu/py.typed
src/dbgpu/tpu.py
src/dbgpu/util.py
src/dbgpu/version.py
src/dbgpu/version.txt
src/dbgpu.egg-info/PKG-INFO
src/dbgpu.egg-info/SOURCES.txt
src/dbgpu.egg-info/dependency_links.txt
src/dbgpu.egg-info/entry_points.txt
src/dbgpu.egg-info/requires.txt
src/dbgpu.egg-info/top_level.txt