Metadata-Version: 2.4
Name: dbgpu
Version: 2025.8
Summary: A small, easy-to-use open source database of over 2000 GPUs with architecture, manufacturing, API support and performance details.
Home-page: https://github.com/painebenjamin/dbgpu
Author: Benjamin Paine
Author-email: painebenjamin@gmail.com
License: MIT
Classifier: Development Status :: 5 - Production/Stable
Classifier: Intended Audience :: Developers
Classifier: Intended Audience :: Education
Classifier: Intended Audience :: Science/Research
Classifier: License :: OSI Approved :: Apache Software License
Classifier: Operating System :: OS Independent
Classifier: Topic :: Scientific/Engineering :: Artificial Intelligence
Classifier: Programming Language :: Python :: 3
Classifier: Programming Language :: Python :: 3.8
Classifier: Programming Language :: Python :: 3.9
Classifier: Programming Language :: Python :: 3.10
Classifier: Programming Language :: Python :: 3.11
Classifier: Programming Language :: Python :: 3.12
Requires-Python: >=3.8.0
License-File: LICENSE
Requires-Dist: click
Requires-Dist: pydantic
Provides-Extra: socks
Requires-Dist: requests[socks]; extra == "socks"
Provides-Extra: tabulate
Requires-Dist: tabulate; extra == "tabulate"
Provides-Extra: fuzz
Requires-Dist: thefuzz; extra == "fuzz"
Provides-Extra: build
Requires-Dist: requests; extra == "build"
Requires-Dist: beautifulsoup4; extra == "build"
Requires-Dist: tqdm; extra == "build"
Provides-Extra: all
Requires-Dist: requests[socks]; extra == "all"
Requires-Dist: tabulate; extra == "all"
Requires-Dist: thefuzz; extra == "all"
Requires-Dist: requests; extra == "all"
Requires-Dist: beautifulsoup4; extra == "all"
Requires-Dist: tqdm; extra == "all"
Dynamic: author
Dynamic: author-email
Dynamic: classifier
Dynamic: description
Dynamic: description-content-type
Dynamic: home-page
Dynamic: license
Dynamic: license-file
Dynamic: provides-extra
Dynamic: requires-dist
Dynamic: requires-python
Dynamic: summary
